pingplusplus/__init__.py
pingplusplus/__main__.py
pingplusplus/application.py
pingplusplus/hostdata.py
pingplusplus/main.py
pingplusplus/ping.py
pingplusplus/ping_worker.py
pingplusplus/screen_layout.py
pingplusplus/settings.py
pingplusplus-1.0.0.dist-info/METADATA
pingplusplus-1.0.0.dist-info/RECORD
pingplusplus-1.0.0.dist-info/WHEEL
pingplusplus-1.0.0.dist-info/entry_points.txt
pingplusplus-1.0.0.dist-info/top_level.txt
viewplusplus/__init__.py
viewplusplus/__main__.py
viewplusplus/main.py
viewplusplus/settings.py
